spider_info_webservice/__init__.py
spider_info_webservice/resources.py
spider_info_webservice/utils.py
tests/__init__.py
spider_info_webservice-0.0.4.dist-info/METADATA
spider_info_webservice-0.0.4.dist-info/WHEEL
spider_info_webservice-0.0.4.dist-info/top_level.txt
spider_info_webservice-0.0.4.dist-info/RECORD
