Metadata-Version: 2.1
Name: spider_info_webservice
Version: 0.0.4
Summary: Scrapy extension for monitoring spider.
Home-page: https://github.com/abebus/spider-info-webservice
Author: abebus
Author-email: anamaev263@gmail.com
Classifier: Programming Language :: Python
Classifier: Programming Language :: Python :: 3.12
Classifier: Programming Language :: Python :: 3.11
Classifier: Programming Language :: Python :: 3.10
Classifier: Programming Language :: Python :: 3.9
Classifier: Programming Language :: Python :: 3.8
Classifier: Operating System :: OS Independent
Classifier: Intended Audience :: Developers
Requires-Python: >=3.8
Requires-Dist: scrapy >=2.6
